aiopypixel/__init__.py
aiopypixel/client.py
aiopypixel/exceptions/__init__.py
aiopypixel/exceptions/exceptions.py
aiopypixel/models/__init__.py
aiopypixel/models/guild.py
aiopypixel/models/player.py
aiopypixel-1.8.2.dist-info/LICENSE.txt
aiopypixel-1.8.2.dist-info/METADATA
aiopypixel-1.8.2.dist-info/WHEEL
aiopypixel-1.8.2.dist-info/top_level.txt
aiopypixel-1.8.2.dist-info/RECORD
