Metadata-Version: 2.1
Name: aiopypixel
Version: 1.8.2
Summary: An asynchronous python wrapper for the Hypixel API.
Home-page: https://github.com/Villager-Dev/aiopypixel
Author: TrustedMercury & Iapetus11
License: UNKNOWN
Platform: UNKNOWN
Classifier: Programming Language :: Python :: 3
Classifier: License :: OSI Approved :: MIT License
Classifier: Operating System :: OS Independent
Requires-Python: >=3.6
